ry_redis_bus/__init__.py
ry_redis_bus/channels.py
ry_redis_bus/helpers.py
ry_redis_bus/ipc_logger.py
ry_redis_bus/py.typed
ry_redis_bus/redis_args.py
ry_redis_bus/redis_client_base.py
ry_redis_bus/redis_client_base_async.py
ry_redis_bus/redis_client_base_sync.py
ry_redis_bus/redis_receiver.py
ry_redis_bus-2.1.8.dist-info/licenses/LICENSE
ry_redis_bus-2.1.8.dist-info/METADATA
ry_redis_bus-2.1.8.dist-info/WHEEL
ry_redis_bus-2.1.8.dist-info/top_level.txt
ry_redis_bus-2.1.8.dist-info/RECORD
