Metadata-Version: 2.4
Name: ry-redis-bus
Version: 2.1.8
Summary: Redis IPC framework for Python and protobuf message types
Author: Ross Yeager
Author-email: ryeager12@email.com
Classifier: Development Status :: 5 - Production/Stable
Classifier: Intended Audience :: Developers
Classifier: License :: OSI Approved :: MIT License
Classifier: Programming Language :: Python :: 3
Classifier: Programming Language :: Python :: 3.12
License-File: LICENSE
Requires-Dist: redis
Requires-Dist: ryutils
Requires-Dist: types-protobuf
Dynamic: author
Dynamic: author-email
Dynamic: classifier
Dynamic: description
Dynamic: description-content-type
Dynamic: license-file
Dynamic: requires-dist
Dynamic: summary
